negmas/__init__.py
negmas/checkpoints.py
negmas/common.py
negmas/config.py
negmas/events.py
negmas/exceptions.py
negmas/ga.py
negmas/generics.py
negmas/inout.py
negmas/mechanisms.py
negmas/mt.py
negmas/protocols.py
negmas/registry.py
negmas/registry_init.py
negmas/serialization.py
negmas/st.py
negmas/utilities.py
negmas/warnings.py
negmas/concurrent/__init__.py
negmas/concurrent/chain.py
negmas/external/__init__.py
negmas/fun/__init__.py
negmas/fun/base.py
negmas/gb/__init__.py
negmas/gb/common.py
negmas/gb/controllers.py
negmas/gb/adapters/__init__.py
negmas/gb/adapters/tau.py
negmas/gb/components/__init__.py
negmas/gb/components/acceptance.py
negmas/gb/components/base.py
negmas/gb/components/concession.py
negmas/gb/components/inverter.py
negmas/gb/components/offering.py
negmas/gb/components/selectors.py
negmas/gb/components/genius/__init__.py
negmas/gb/components/genius/acceptance.py
negmas/gb/components/genius/base.py
negmas/gb/components/genius/models.py
negmas/gb/components/genius/offering.py
negmas/gb/components/models/__init__.py
negmas/gb/components/models/ufun.py
negmas/gb/constraints/__init__.py
negmas/gb/constraints/base.py
negmas/gb/constraints/rfo.py
negmas/gb/constraints/rlo.py
negmas/gb/constraints/unique.py
negmas/gb/evaluators/__init__.py
negmas/gb/evaluators/base.py
negmas/gb/evaluators/gao.py
negmas/gb/evaluators/tau.py
negmas/gb/mechanisms/__init__.py
negmas/gb/mechanisms/base.py
negmas/gb/mechanisms/tau.py
negmas/gb/mechanisms/tauserial.py
negmas/gb/negotiators/__init__.py
negmas/gb/negotiators/base.py
negmas/gb/negotiators/cab.py
negmas/gb/negotiators/hybrid.py
negmas/gb/negotiators/limited.py
negmas/gb/negotiators/micro.py
negmas/gb/negotiators/nice.py
negmas/gb/negotiators/randneg.py
negmas/gb/negotiators/timebased.py
negmas/gb/negotiators/titfortat.py
negmas/gb/negotiators/tough.py
negmas/gb/negotiators/utilbased.py
negmas/gb/negotiators/war.py
negmas/gb/negotiators/modular/__init__.py
negmas/gb/negotiators/modular/boa.py
negmas-0.14.0.dist-info/licenses/AUTHORS.rst
negmas-0.14.0.dist-info/licenses/LICENSE
negmas-0.14.0.dist-info/METADATA
negmas-0.14.0.dist-info/WHEEL
negmas-0.14.0.dist-info/entry_points.txt
negmas-0.14.0.dist-info/top_level.txt
negmas-0.14.0.dist-info/RECORD
