Metadata-Version: 2.4
Name: negmas
Version: 0.14.0
Summary: NEGotiations Managed by Agent Simulations
Author-email: Yasser Mohammad <yasserfarouk@gmail.com>
License-Expression: AGPL-3.0-or-later
Classifier: Programming Language :: Python :: 3
Classifier: Programming Language :: Python :: 3.10
Classifier: Programming Language :: Python :: 3.11
Classifier: Programming Language :: Python :: 3.12
Classifier: Programming Language :: Python :: 3.13
Classifier: Programming Language :: Python :: 3.14
Classifier: Programming Language :: Python :: Implementation :: CPython
Requires-Python: >=3.10
License-File: LICENSE
License-File: AUTHORS.rst
Requires-Dist: attrs>=24.2.0
Requires-Dist: click>=8.1.7
Requires-Dist: click-config-file>=0.6.0
Requires-Dist: cloudpickle>=3.1.0
Requires-Dist: colorlog>=6.9.0
Requires-Dist: dill>=0.3.9
Requires-Dist: gif>=23.3.0
Requires-Dist: inflect<6.0,>=4.1.0
Requires-Dist: plotly>=5.18.0
Requires-Dist: kaleido>=0.2.1
Requires-Dist: pillow>=12.1.0
Requires-Dist: networkx>=3.4.2
Requires-Dist: psutil>=6.1.0
Requires-Dist: py4j>=0.10.9.7
Requires-Dist: rich>=13.9.4
Requires-Dist: scikit-learn>=1.5.2
Requires-Dist: setuptools>=75.5.0
Requires-Dist: stringcase>=1.2.0
Requires-Dist: tabulate>=0.9.0
Requires-Dist: typer>=0.13.0
Requires-Dist: pyyaml>=6.0.2
Requires-Dist: typing-extensions>=4.12.2
Requires-Dist: pandas>=2.2.3
Requires-Dist: scipy>=1.14.1
Requires-Dist: numpy
Requires-Dist: pyarrow>=22.0.0
Provides-Extra: gui
Requires-Dist: pyqt5>=5.15.11; extra == "gui"
Provides-Extra: testing
Requires-Dist: hypothesis>=6.118.8; extra == "testing"
Requires-Dist: pytest-check>=2.4.1; extra == "testing"
Requires-Dist: pytest-timeout>=2.3.1; extra == "testing"
Requires-Dist: pytest>=8.3.3; extra == "testing"
Provides-Extra: docs
Requires-Dist: nbformat>=5.10.4; extra == "docs"
Requires-Dist: nbsphinx>=0.9.6; extra == "docs"
Requires-Dist: notebook==6.4.12; extra == "docs"
Requires-Dist: pillow>=12.1.0; extra == "docs"
Requires-Dist: sphinx>=7.0.0; extra == "docs"
Requires-Dist: sphinx-autodoc-typehints<3.0.0,>=2.0.0; python_version < "3.11" and extra == "docs"
Requires-Dist: sphinx-autodoc-typehints>=3.0.0; python_version >= "3.11" and extra == "docs"
Requires-Dist: sphinx-tabs>=3.4.7; extra == "docs"
Requires-Dist: sphinx-copybutton>=0.5.2; extra == "docs"
Requires-Dist: sphinx-click>=6.0.0; extra == "docs"
Requires-Dist: sphinxcontrib-typer>=0.5.0; extra == "docs"
Requires-Dist: furo>=2024.1.29; extra == "docs"
Provides-Extra: dev
Requires-Dist: bumpversion>=0.6.0; extra == "dev"
Requires-Dist: codacy-coverage>=1.3.11; extra == "dev"
Requires-Dist: coverage>=7.6.5; extra == "dev"
Requires-Dist: docutils>=0.21.2; extra == "dev"
Requires-Dist: ipykernel>=6.29.5; extra == "dev"
Requires-Dist: jupyter>=1.1.1; extra == "dev"
Requires-Dist: markupsafe>=3.0.2; extra == "dev"
Requires-Dist: pandoc>=2.4; extra == "dev"
Requires-Dist: papermill>=2.6.0; extra == "dev"
Requires-Dist: pre-commit>=4.0.1; extra == "dev"
Requires-Dist: pytest-cov>=6.0.0; extra == "dev"
Requires-Dist: pytest-sugar>=1.0.0; extra == "dev"
Requires-Dist: readme-renderer>=44.0; extra == "dev"
Requires-Dist: recommonmark>=0.7.1; extra == "dev"
Requires-Dist: ruff>=0.11.0; extra == "dev"
Requires-Dist: seaborn>=0.13.0; extra == "dev"
Requires-Dist: tox>=4.23.2; extra == "dev"
Requires-Dist: twine>=5.1.1; extra == "dev"
Requires-Dist: wheel>=0.45.0; extra == "dev"
Dynamic: license-file
